django_task_queue/__init__.py
django_task_queue/_exc.py
django_task_queue/_queues.py
django_task_queue/_types.py
django_task_queue/_util.py
django_task_queue/_workers.py
django_task_queue/admin.py
django_task_queue/apps.py
django_task_queue/examples.py
django_task_queue/models.py
django_task_queue/tests.py
django_task_queue/management/__init__.py
django_task_queue/management/commands/__init__.py
django_task_queue/management/commands/dtq_createrandomtasks.py
django_task_queue/management/commands/dtq_startworkers.py
django_task_queue/migrations/0001_initial.py
django_task_queue/migrations/__init__.py
django_task_queue-6.1.2.dist-info/LICENSE
django_task_queue-6.1.2.dist-info/METADATA
django_task_queue-6.1.2.dist-info/WHEEL
django_task_queue-6.1.2.dist-info/top_level.txt
django_task_queue-6.1.2.dist-info/RECORD
