Metadata-Version: 2.2
Name: django-task-queue
Version: 6.1.2
Summary: Simple task queue for the Python Django web framework
Home-page: https://github.com/ross-sharma/django-task-queue
Author: Ross Sharma
Author-email: ross@ross-sharma.com
License: MIT
Classifier: License :: OSI Approved :: MIT License
Classifier: Programming Language :: Python :: 3
License-File: LICENSE
Requires-Dist: django
Dynamic: author
Dynamic: author-email
Dynamic: classifier
Dynamic: description
Dynamic: description-content-type
Dynamic: home-page
Dynamic: license
Dynamic: requires-dist
Dynamic: summary
